nonebot_plugin_specify_broadcast/__init__.py
nonebot_plugin_specify_broadcast/config.py
nonebot_plugin_specify_broadcast-1.0.6.dist-info/LICENSE
nonebot_plugin_specify_broadcast-1.0.6.dist-info/METADATA
nonebot_plugin_specify_broadcast-1.0.6.dist-info/WHEEL
nonebot_plugin_specify_broadcast-1.0.6.dist-info/top_level.txt
nonebot_plugin_specify_broadcast-1.0.6.dist-info/RECORD
