Metadata-Version: 2.1
Name: nonebot-plugin-specify-broadcast
Version: 1.0.6
Summary: A NoneBot plugin for broadcasting messages to multiple group chats.
Author-email: f1justin <f1justin@outlook.com>
License: GNU GENERAL PUBLIC LICENSE
Project-URL: homepage, https://github.com/F1Justin/nonebot-plugin-specify-broadcast
Project-URL: repository, https://github.com/F1Justin/nonebot-plugin-specify-broadcast
Project-URL: documentation, https://github.com/F1Justin/nonebot-plugin-specify-broadcast
Project-URL: Bug Tracker, https://github.com/F1Justin/nonebot-plugin-specify-broadcast/issues
Project-URL: Source Code, https://github.com/F1Justin/nonebot-plugin-specify-broadcast
Keywords: nonebot,plugin,broadcast,group,bot
Requires-Python: >=3.8
License-File: LICENSE
Requires-Dist: nonebot2>=2.2.0
Requires-Dist: nonebot-adapter-onebot>=2.0.0
Requires-Dist: nonebot-plugin-apscheduler>=0.1.0
